photonflux/__init__.py
photonflux/circuit.py
photonflux/mplstyle.mplstyle
photonflux/component_models/Base_model.py
photonflux/component_models/default_model_dict.py
photonflux/component_models/bends/bend_circular.py
photonflux/component_models/bends/bend_euler.py
photonflux/component_models/heater/TiN_heater.py
photonflux/component_models/heater/TiN_heater_modeling.ipynb
photonflux/component_models/heater/TiN_heater_sweep.pkl
photonflux/component_models/heater/TiN_heater_undercut.pkl
photonflux/component_models/heater/base_TiN_heater.ldev
photonflux/component_models/heater/base_TiN_heater.lms
photonflux/component_models/heater/base_TiN_heater_undercut.ldev
photonflux/component_models/heater/base_doped_heater.ldev
photonflux/component_models/heater/base_doped_heater.lms
photonflux/component_models/heater/base_doped_heater_undercut.ldev
photonflux/component_models/heater/doped_heater_modeling.ipynb
photonflux/component_models/heater/doped_heater_sweep.pkl
photonflux/component_models/heater/doped_heater_undercut_sweep.pkl
photonflux/component_models/laser/laser.py
photonflux/component_models/photodetector/photodetector.py
photonflux/component_models/pn_pin_junction/MOSCAP_doping.pkl
photonflux/component_models/pn_pin_junction/U_doping.pkl
photonflux/component_models/pn_pin_junction/lateral_doping.pkl
photonflux/component_models/pn_pin_junction/lumerical_MOSCAP_junction_sweep.ipynb
photonflux/component_models/pn_pin_junction/lumerical_U_shaped_junction_sweep.ipynb
photonflux/component_models/pn_pin_junction/lumerical_lateral_junction_sweep.ipynb
photonflux/component_models/pn_pin_junction/lumerical_vertical_junction_sweep.ipynb
photonflux/component_models/pn_pin_junction/pn_phase_shifter_design.ipynb
photonflux/component_models/pn_pin_junction/straight_pn.py
photonflux/component_models/pn_pin_junction/vertical_doping.pkl
photonflux/component_models/pn_pin_junction/lumerical_files/base_MOSCAP_junction.ldev
photonflux-0.2.3.dist-info/LICENSE
photonflux-0.2.3.dist-info/WHEEL
photonflux-0.2.3.dist-info/METADATA
photonflux-0.2.3.dist-info/RECORD
