Metadata-Version: 2.1
Name: photonflux
Version: 0.2.3
Summary: Photonic circuit network simulator
Keywords: eda,photonics,python
Author-email: Alexander Sludds <alexsludds@gmail.com>
Requires-Python: >=3.7
Classifier: Programming Language :: Python :: 3.7
Classifier: Programming Language :: Python :: 3.8
Classifier: Programming Language :: Python :: 3.9
Classifier: Programming Language :: Python :: 3.10
Classifier: Programming Language :: Python :: 3.11
Classifier: Operating System :: OS Independent
Requires-Dist: networkx
Requires-Dist: matplotlib
Requires-Dist: gdsfactory
Requires-Dist: numpy
Requires-Dist: scipy
Requires-Dist: tqdm
Requires-Dist: seaborn
